Workbook

Sheet Premissas
A1: PREMISSAS DO MODELO — edite as células AZUIS (amarelas = mais sensíveis)
A3: TMA recomendada (a.a.) | B3: 0.2
A4: TMA piso / custo de oportunidade (a.a.) | B4: 0.1425
A5: TMA estresse (a.a.) | B5: 0.3
A6: Investimento software/MVP (Ano 0, R$) | B6: 380000
A7: Fazenda média (ha por cliente) | B7: 3000
A8: A) SaaS - preço (R$/ha/ano) | B8: 40
A9: A) SaaS - custo variável (% receita) | B9: 0.3
A10: B) DaaS - preço (R$/ha/ano) | B10: 80
A11: B) DaaS - capacidade (ha/ano por unidade) | B11: 12000
A12: B) DaaS - custo por unidade (CAPEX, R$) | B12: 120000
A13: B) DaaS - custo variável (% receita) | B13: 0.72
A14: C) Híbrido - preço SaaS (R$/ha/ano) | B14: 40
... A16: C) Híbrido - custo variável (% receita) | B16: 0.3
A18: Série anual | C18: Ano 1 | D18: Ano 2 | E18: Ano 3 | F18: Ano 4 | G18: Ano 5
A19: Hectares ativos (acum.) | C19: 25000 | D19: 50000 | E19: 80000 | F19: 115000 | G19: 150000
A20: Hectares novos no ano | C20: 25000 | D20: 25000 | E20: 30000 | F20: 35000 | G20: 35000
A21: Custo fixo base A/C (R$) | C21: 900000 | D21: 1150000 | E21: 1500000 | F21: 1850000 | G21: 2200000
A22: Custo fixo DaaS B (R$) | C22: 900000 | D22: 1150000 | E22: 1500000 | F22: 1850000 | G22: 2200000
A24: Azul = input editável | Preto = fórmula | Verde = link entre abas | Amarelo = premissa-chave

Sheet Modelo A — SaaS
A1: Modelo A — SaaS
A2: t (período) | B2: 0 | C2: 1 | D2: 2 | E2: 3 | F2: 4 | G2: 5
A3: Hectares ativos | B3: 0 | C3: =Premissas!C19 -> 25000 | D3: =Premissas!D19 -> 50000 | E3: =Premissas!E19 -> 80000 | F3: =Premissas!F19 -> 115000 | G3: =Premissas!G19 -> 150000
A4: Unidades necessárias (acum.) | B4: 0 | C4: 0 | D4: 0 | E4: 0 | F4: 0 | G4: 0
A5: Receita (R$) | B5: 0 | C5: =C3*Premissas!$B$8 -> 1000000 | D5: =D3*Premissas!$B$8 -> 2000000 | E5: =E3*Premissas!$B$8 -> 3200000 | F5: =F3*Premissas!$B$8 -> 4600000 | G5: =G3*Premissas!$B$8 -> 6000000
A6: Custo variável (R$) | B6: 0 | C6: =C5*Premissas!$B$9 -> 300000 | D6: =D5*Premissas!$B$9 -> 600000 | E6: =E5*Premissas!$B$9 -> 960000 | F6: =F5*Premissas!$B$9 -> 1380000 | G6: =G5*Premissas!$B$9 -> 1800000
A7: Custo fixo (R$) | B7: 0 | C7: =Premissas!C21 -> 900000 | D7: =Premissas!D21 -> 1150000 | E7: =Premissas!E21 -> 1500000 | F7: =Premissas!F21 -> 1850000 | G7: =Premissas!G21 -> 2200000
A8: CAPEX (R$) | B8: =Premissas!$B$6 -> 380000 | C8: 0 | D8: 0 | E8: 0 | F8: 0 | G8: 0
A9: Fluxo de caixa líquido (R$) | B9: =B5-B6-B7-B8 -> -380000 | C9: =C5-C6-C7-C8 -> -200000 | D9: =D5-D6-D7-D8 -> 250000 | E9: =E5-E6-E7-E8 -> 740000 | F9: =F5-F6-F7-F8 -> 1370000 | G9: =G5-G6-G7-G8 -> 2000000
A10: Fluxo acumulado (R$) | B10: =B9 -> -380000 | C10: =B10+C9 -> -580000 | D10: =C10+D9 -> -330000 | E10: =D10+E9 -> 410000 | F10: =E10+F9 -> 1780000 | G10: =F10+G9 -> 3780000
A11: Fator de desconto | B11: =1/(1+Premissas!$B$3)^B2 -> 1 | C11: =1/(1+Premissas!$B$3)^C2 -> 0.83333333 | D11: =1/(1+Premissas!$B$3)^D2 -> 0.69444444 | E11: =1/(1+Premissas!$B$3)^E2 -> 0.5787037 | F11: =1/(1+Premissas!$B$3)^F2 -> 0.48225309 | G11: =1/(1+Premissas!$B$3)^G2 -> 0.40187757
A12: Fluxo descontado (R$) | B12: =B9*B11 -> -380000 | C12: =C9*C11 -> -166666.67 | D12: =D9*D11 -> 173611.11 | E12: =E9*E11 -> 428240.74 | F12: =F9*F11 -> 660686.73 | G12: =G9*G11 -> 803755.14
A13: Fluxo desc. acumulado (R$) | B13: =B12 -> -380000 | C13: =B13+C12 -> -546666.67 | D13: =C13+D12 -> -373055.56 | E13: =D13+E12 -> 55185.185 | F13: =E13+F12 -> 715871.91 | G13: =F13+G12 -> 1519627.1
A15: VPL (TMA recomendada, R$) | B15: =SUM(B12:G12) -> 1519627.1
A16: TIR (a.a.) | B16: =IRR(B9:G9) -> 0.74304636
A17: Payback simples (anos) | B17: {=IF(G10<0,"Não recupera",(COUNTIF(B10:G10,"<0")-1)+(-INDEX(B10:G10,COUNTIF(B10:G10,"<0")))/INDEX(B9:G9,COUNTIF(B10:G10,"<0")+1))} -> 2.4459459
A18: Payback descontado (anos) | B18: {=IF(G13<0,"Não recupera",(COUNTIF(B13:G13,"<0")-1)+(-INDEX(B13:G13,COUNTIF(B13:G13,"<0")))/INDEX(B12:G12,COUNTIF(B13:G13,"<0")+1))} -> 2.8711351
A19: IBC (Índice Benefício/Custo) | B19: =SUM(C12:G12)/(-B9) -> 4.9990186
A20: ROIA (a.a.) | B20: =B19^(1/5)-1 -> 0.37967549
A21: VPL @ TMA piso (R$) | B21: {=NPV(Premissas!$B$4,C9:G9)+B9} -> 1964174.2
A22: VPL @ TMA estresse (R$) | B22: {=NPV(Premissas!$B$5,C9:G9)+B9} -> 969239.01
A24: Premissas em Premissas! ; payback assume um único cruzamento de sinal no fluxo acumulado.

Sheet Modelo B — DaaS
A1: Modelo B — DaaS
A2: t (período) | B2: 0 | C2: 1 | D2: 2 | E2: 3 | F2: 4 | G2: 5
A3: Hectares ativos | B3: 0 | C3: =Premissas!C19 -> 25000 | D3: =Premissas!D19 -> 50000 | E3: =Premissas!E19 -> 80000 | F3: =Premissas!F19 -> 115000 | G3: =Premissas!G19 -> 150000
A4: Unidades necessárias (acum.) | B4: 0 | C4: =CEILING(C3/Premissas!$B$11,1) -> 3 | D4: =CEILING(D3/Premissas!$B$11,1) -> 5 | E4: =CEILING(E3/Premissas!$B$11,1) -> 7 | F4: =CEILING(F3/Premissas!$B$11,1) -> 10 | G4: =CEILING(G3/Premissas!$B$11,1) -> 13
A5: Receita (R$) | B5: 0 | C5: =C3*Premissas!$B$10 -> 2000000 | D5: =D3*Premissas!$B$10 -> 4000000 | E5: =E3*Premissas!$B$10 -> 6400000 | F5: =F3*Premissas!$B$10 -> 9200000 | G5: =G3*Premissas!$B$10 -> 12000000
A6: Custo variável (R$) | B6: 0 | C6: =C5*Premissas!$B$13 -> 1440000 | D6: =D5*Premissas!$B$13 -> 2880000 | E6: =E5*Premissas!$B$13 -> 4608000 | F6: =F5*Premissas!$B$13 -> 6624000 | G6: =G5*Premissas!$B$13 -> 8640000
A7: Custo fixo (R$) | B7: 0 | C7: =Premissas!C22 -> 900000 | D7: =Premissas!D22 -> 1150000 | E7: =Premissas!E22 -> 1500000 | F7: =Premissas!F22 -> 1850000 | G7: =Premissas!G22 -> 2200000
A8: CAPEX (R$) | B8: =Premissas!$B$6 -> 380000 | C8: =(C4-B4)*Premissas!$B$12 -> 360000 | D8: =(D4-C4)*Premissas!$B$12 -> 240000 | E8: =(E4-D4)*Premissas!$B$12 -> 240000 | F8: =(F4-E4)*Premissas!$B$12 -> 360000 | G8: =(G4-F4)*Premissas!$B$12 -> 360000
A9: Fluxo de caixa líquido (R$) | B9: =B5-B6-B7-B8 -> -380000 | C9: =C5-C6-C7-C8 -> -700000 | D9: =D5-D6-D7-D8 -> -270000 | E9: =E5-E6-E7-E8 -> 52000 | F9: =F5-F6-F7-F8 -> 366000 | G9: =G5-G6-G7-G8 -> 800000
A10: Fluxo acumulado (R$) | B10: =B9 -> -380000 | C10: =B10+C9 -> -1080000 | D10: =C10+D9 -> -1350000 | E10: =D10+E9 -> -1298000 | F10: =E10+F9 -> -932000 | G10: =F10+G9 -> -132000
A11: Fator de desconto | B11: =1/(1+Premissas!$B$3)^B2 -> 1 | C11: =1/(1+Premissas!$B$3)^C2 -> 0.83333333 | D11: =1/(1+Premissas!$B$3)^D2 -> 0.69444444 | E11: =1/(1+Premissas!$B$3)^E2 -> 0.5787037 | F11: =1/(1+Premissas!$B$3)^F2 -> 0.48225309 | G11: =1/(1+Premissas!$B$3)^G2 -> 0.40187757
A12: Fluxo descontado (R$) | B12: =B9*B11 -> -380000 | C12: =C9*C11 -> -583333.33 | D12: =D9*D11 -> -187500 | E12: =E9*E11 -> 30092.593 | F12: =F9*F11 -> 176504.63 | G12: =G9*G11 -> 321502.06
A13: Fluxo desc. acumulado (R$) | B13: =B12 -> -380000 | C13: =B13+C12 -> -963333.33 | D13: =C13+D12 -> -1150833.3 | E13: =D13+E12 -> -1120740.7 | F13: =E13+F12 -> -944236.11 | G13: =F13+G12 -> -622734.05
A15: VPL (TMA recomendada, R$) | B15: =SUM(B12:G12) -> -622734.05
A16: TIR (a.a.) | B16: =IRR(B9:G9) -> -0.027474167
A17: Payback simples (anos) | B17: {=IF(G10<0,"Não recupera",(COUNTIF(B10:G10,"<0")-1)+(-INDEX(B10:G10,COUNTIF(B10:G10,"<0")))/INDEX(B9:G9,COUNTIF(B10:G10,"<0")+1))} -> Não recupera
A18: Payback descontado (anos) | B18: {=IF(G13<0,"Não recupera",(COUNTIF(B13:G13,"<0")-1)+(-INDEX(B13:G13,COUNTIF(B13:G13,"<0")))/INDEX(B12:G12,COUNTIF(B13:G13,"<0")+1))} -> Não recupera
A19: IBC (Índice Benefício/Custo) | B19: =SUM(C12:G12)/(-B9) -> -0.63877383
A20: ROIA (a.a.) | B20: =B19^(1/5)-1 -> -1.9142594
A21: VPL @ TMA piso (R$) | B21: {=NPV(Premissas!$B$4,C9:G9)+B9} -> -538891.1
A22: VPL @ TMA estresse (R$) | B22: {=NPV(Premissas!$B$5,C9:G9)+B9} -> -710946.18
A24: Premissas em Premissas! ; payback assume um único cruzamento de sinal no fluxo acumulado.

Sheet Modelo C — Híbrido
A1: Modelo C — Híbrido
A2: t (período) | B2: 0 | C2: 1 | D2: 2 | E2: 3 | F2: 4 | G2: 5
A3: Hectares ativos | B3: 0 | C3: =Premissas!C19 -> 25000 | D3: =Premissas!D19 -> 50000 | E3: =Premissas!E19 -> 80000 | F3: =Premissas!F19 -> 115000 | G3: =Premissas!G19 -> 150000
A4: Unidades necessárias (acum.) | B4: 0 | C4: 0 | D4: 0 | E4: 0 | F4: 0 | G4: 0
A5: Receita (R$) | B5: 0 | C5: =C3*Premissas!$B$14+(Premissas!C20/Premissas!$B$7)*Premissas!$B$15 -> 1166666.7 | D5: =D3*Premissas!$B$14+(Premissas!D20/Premissas!$B$7)*Premissas!$B$15 -> 2166666.7 | E5: =E3*Premissas!$B$14+(Premissas!E20/Premissas!$B$7)*Premissas!$B$15 -> 3400000 | F5: =F3*Premissas!$B$14+(Premissas!F20/Premissas!$B$7)*Premissas!$B$15 -> 4833333.3 | G5: =G3*Premissas!$B$14+(Premissas!G20/Premissas!$B$7)*Premissas!$B$15 -> 6233333.3
A6: Custo variável (R$) | B6: 0 | C6: =C5*Premissas!$B$16 -> 350000 | D6: =D5*Premissas!$B$16 -> 650000 | E6: =E5*Premissas!$B$16 -> 1020000 | F6: =F5*Premissas!$B$16 -> 1450000 | G6: =G5*Premissas!$B$16 -> 1870000
A7: Custo fixo (R$) | B7: 0 | C7: =Premissas!C21 -> 900000 | D7: =Premissas!D21 -> 1150000 | E7: =Premissas!E21 -> 1500000 | F7: =Premissas!F21 -> 1850000 | G7: =Premissas!G21 -> 2200000
A8: CAPEX (R$) | B8: =Premissas!$B$6 -> 380000 | C8: 0 | D8: 0 | E8: 0 | F8: 0 | G8: 0
A9: Fluxo de caixa líquido (R$) | B9: =B5-B6-B7-B8 -> -380000 | C9: =C5-C6-C7-C8 -> -83333.333 | D9: =D5-D6-D7-D8 -> 366666.67 | E9: =E5-E6-E7-E8 -> 880000 | F9: =F5-F6-F7-F8 -> 1533333.3 | G9: =G5-G6-G7-G8 -> 2163333.3
A10: Fluxo acumulado (R$) | B10: =B9 -> -380000 | C10: =B10+C9 -> -463333.33 | D10: =C10+D9 -> -96666.667 | E10: =D10+E9 -> 783333.33 | F10: =E10+F9 -> 2316666.7 | G10: =F10+G9 -> 4480000
A11: Fator de desconto | B11: =1/(1+Premissas!$B$3)^B2 -> 1 | C11: =1/(1+Premissas!$B$3)^C2 -> 0.83333333 | D11: =1/(1+Premissas!$B$3)^D2 -> 0.69444444 | E11: =1/(1+Premissas!$B$3)^E2 -> 0.5787037 | F11: =1/(1+Premissas!$B$3)^F2 -> 0.48225309 | G11: =1/(1+Premissas!$B$3)^G2 -> 0.40187757
A12: Fluxo descontado (R$) | B12: =B9*B11 -> -380000 | C12: =C9*C11 -> -69444.444 | D12: =D9*D11 -> 254629.63 | E12: =E9*E11 -> 509259.26 | F12: =F9*F11 -> 739454.73 | G12: =G9*G11 -> 869395.15
A13: Fluxo desc. acumulado (R$) | B13: =B12 -> -380000 | C13: =B13+C12 -> -449444.44 | D13: =C13+D12 -> -194814.81 | E13: =D13+E12 -> 314444.44 | F13: =E13+F12 -> 1053899.2 | G13: =F13+G12 -> 1923294.3
A15: VPL (TMA recomendada, R$) | B15: =SUM(B12:G12) -> 1923294.3
A16: TIR (a.a.) | B16: =IRR(B9:G9) -> 0.91471576
A17: Payback simples (anos) | B17: {=IF(G10<0,"Não recupera",(COUNTIF(B10:G10,"<0")-1)+(-INDEX(B10:G10,COUNTIF(B10:G10,"<0")))/INDEX(B9:G9,COUNTIF(B10:G10,"<0")+1))} -> 2.1098485
A18: Payback descontado (anos) | B18: {=IF(G13<0,"Não recupera",(COUNTIF(B13:G13,"<0")-1)+(-INDEX(B13:G13,COUNTIF(B13:G13,"<0")))/INDEX(B12:G12,COUNTIF(B13:G13,"<0")+1))} -> 2.3825455
A19: IBC (Índice Benefício/Custo) | B19: =SUM(C12:G12)/(-B9) -> 6.0613009
A20: ROIA (a.a.) | B20: =B19^(1/5)-1 -> 0.43388119
A21: VPL @ TMA piso (R$) | B21: {=NPV(Premissas!$B$4,C9:G9)+B9} -> 2429314.1
A22: VPL @ TMA estresse (R$) | B22: {=NPV(Premissas!$B$5,C9:G9)+B9} -> 1292917.3
A24: Premissas em Premissas! ; payback assume um único cruzamento de sinal no fluxo acumulado.

Sheet Comparativo
A1: COMPARATIVO DOS 3 MODELOS (à TMA recomendada)
A3: Indicador | B3: A) SaaS asset-light | C3: B) DaaS frota própria | D3: C) Híbrido (setup+SaaS)
A4: Investimento Ano 0 (R$) | B4: =-'Modelo A — SaaS'!B9 -> 380000 | C4: =-'Modelo B — DaaS'!B9 -> 380000 | D4: =-'Modelo C — Híbrido'!B9 -> 380000
A5: VPL (TMA recom., R$) | B5: ='Modelo A — SaaS'!B15 -> 1519627.1 | C5: ='Modelo B — DaaS'!B15 -> -622734.05 | D5: ='Modelo C — Híbrido'!B15 -> 1923294.3
A6: VPL (TMA piso, R$) | B6: ='Modelo A — SaaS'!B21 -> 1964174.2 | C6: ='Modelo B — DaaS'!B21 -> -538891.1 | D6: ='Modelo C — Híbrido'!B21 -> 2429314.1
A7: VPL (TMA estresse, R$) | B7: ='Modelo A — SaaS'!B22 -> 969239.01 | C7: ='Modelo B — DaaS'!B22 -> -710946.18 | D7: ='Modelo C — Híbrido'!B22 -> 1292917.3
A8: TIR (a.a.) | B8: ='Modelo A — SaaS'!B16 -> 0.74304636 | C8: ='Modelo B — DaaS'!B16 -> -0.027474167 | D8: ='Modelo C — Híbrido'!B16 -> 0.91471576
A9: Payback simples (anos) | B9: ='Modelo A — SaaS'!B17 -> 2.4459459 | C9: ='Modelo B — DaaS'!B17 -> Não recupera | D9: ='Modelo C — Híbrido'!B17 -> 2.1098485
A10: Payback descontado (anos) | B10: ='Modelo A — SaaS'!B18 -> 2.8711351 | C10: ='Modelo B — DaaS'!B18 -> Não recupera | D10: ='Modelo C — Híbrido'!B18 -> 2.3825455
A11: IBC | B11: ='Modelo A — SaaS'!B19 -> 4.9990186 | C11: ='Modelo B — DaaS'!B19 -> -0.63877383 | D11: ='Modelo C — Híbrido'!B19 -> 6.0613009
A12: ROIA (a.a.) | B12: ='Modelo A — SaaS'!B20 -> 0.37967549 | C12: ='Modelo B — DaaS'!B20 -> -1.9142594 | D12: ='Modelo C — Híbrido'!B20 -> 0.43388119
A15: Recomendação: C (Híbrido) como principal — maior VPL e menor payback; A (SaaS) como alternativa enxuta; B (DaaS frota própria) é inviável (VPL negativo em todos os níveis de TMA testados) — rejeitar como núcleo.

Sheet Sensibilidade
A1: ANÁLISE DE SENSIBILIDADE — Modelo C (motor: adoção e preço)
A3: Multiplicadores | B3: Pessimista | C3: Base | D3: Otimista
A4: Mult. adoção (hectares) | B4: 0.6 | C4: 1 | D4: 1.25
A5: Mult. preço | B5: 0.85 | C5: 1 | D5: 1.1
A6: Mult. custo fixo | B6: 0.8 | C6: 1 | D6: 1.05
A8: Fluxo de caixa (R$) por ano
A9: Ano 0 | B9: =-Premissas!$B$6 -> -380000 | C9: =-Premissas!$B$6 -> -380000 | D9: =-Premissas!$B$6 -> -380000
A10: Ano 1 | B10: =((Premissas!$C$19*B$4*Premissas!$B$14*B$5)+((Premissas!$C$20*B$4/Premissas!$B$7)*Premissas!$B$15))*(1-Premissas!$B$16)-Premissas!$C$21*B$6 -> -293000 | C10: =((Premissas!$C$19*C$4*Premissas!$B$14*C$5)+((Premissas!$C$20*C$4/Premissas!$B$7)*Premissas!$B$15))*(1-Premissas!$B$16)-Premissas!$C$21*C$6 -> -83333.333 | D10: =((Premissas!$C$19*D$4*Premissas!$B$14*D$5)+((Premissas!$C$20*D$4/Premissas!$B$7)*Premissas!$B$15))*(1-Premissas!$B$16)-Premissas!$C$21*D$6 -> 163333.33
A11: Ano 2 | B11: =((Premissas!$D$19*B$4*Premissas!$B$14*B$5)+((Premissas!$D$20*B$4/Premissas!$B$7)*Premissas!$B$15))*(1-Premissas!$B$16)-Premissas!$D$21*B$6 -> -136000 | C11: =((Premissas!$D$19*C$4*Premissas!$B$14*C$5)+((Premissas!$D$20*C$4/Premissas!$B$7)*Premissas!$B$15))*(1-Premissas!$B$16)-Premissas!$D$21*C$6 -> 366666.67 | D11: =((Premissas!$D$19*D$4*Premissas!$B$14*D$5)+((Premissas!$D$20*D$4/Premissas!$B$7)*Premissas!$B$15))*(1-Premissas!$B$16)-Premissas!$D$21*D$6 -> 863333.33
A12: Ano 3 | B12: =((Premissas!$E$19*B$4*Premissas!$B$14*B$5)+((Premissas!$E$20*B$4/Premissas!$B$7)*Premissas!$B$15))*(1-Premissas!$B$16)-Premissas!$E$21*B$6 -> 26400 | C12: =((Premissas!$E$19*C$4*Premissas!$B$14*C$5)+((Premissas!$E$20*C$4/Premissas!$B$7)*Premissas!$B$15))*(1-Premissas!$B$16)-Premissas!$E$21*C$6 -> 880000 | D12: =((Premissas!$E$19*D$4*Premissas!$B$14*D$5)+((Premissas!$E$20*D$4/Premissas!$B$7)*Premissas!$B$15))*(1-Premissas!$B$16)-Premissas!$E$21*D$6 -> 1680000
A13: Ano 4 | B13: =((Premissas!$F$19*B$4*Premissas!$B$14*B$5)+((Premissas!$F$20*B$4/Premissas!$B$7)*Premissas!$B$15))*(1-Premissas!$B$16)-Premissas!$F$21*B$6 -> 260200 | C13: =((Premissas!$F$19*C$4*Premissas!$B$14*C$5)+((Premissas!$F$20*C$4/Premissas!$B$7)*Premissas!$B$15))*(1-Premissas!$B$16)-Premissas!$F$21*C$6 -> 1533333.3 | D13: =((Premissas!$F$19*D$4*Premissas!$B$14*D$5)+((Premissas!$F$20*D$4/Premissas!$B$7)*Premissas!$B$15))*(1-Premissas!$B$16)-Premissas!$F$21*D$6 -> 2689166.7
A14: Ano 5 | B14: =((Premissas!$G$19*B$4*Premissas!$B$14*B$5)+((Premissas!$G$20*B$4/Premissas!$B$7)*Premissas!$B$15))*(1-Premissas!$B$16)-Premissas!$G$21*B$6 -> 480000 | C14: =((Premissas!$G$19*C$4*Premissas!$B$14*C$5)+((Premissas!$G$20*C$4/Premissas!$B$7)*Premissas!$B$15))*(1-Premissas!$B$16)-Premissas!$G$21*C$6 -> 2163333.3 | D14: =((Premissas!$G$19*D$4*Premissas!$B$14*D$5)+((Premissas!$G$20*D$4/Premissas!$B$7)*Premissas!$B$15))*(1-Premissas!$B$16)-Premissas!$G$21*D$6 -> 3669166.7
A16: VPL @ TMA recomendada (R$) | B16: {=NPV(Premissas!$B$3,B10:B14)+B9} -> -384949.85 | C16: {=NPV(Premissas!$B$3,C10:C14)+C9} -> 1923294.3 | D16: {=NPV(Premissas!$B$3,D10:D14)+D9} -> 4099285.1
A17: VPL @ TMA piso (R$) | B17: {=NPV(Premissas!$B$4,B10:B14)+B9} -> -323646.12 | C17: {=NPV(Premissas!$B$4,C10:C14)+C9} -> 2429314.1 | D17: {=NPV(Premissas!$B$4,D10:D14)+D9} -> 5014092.5
A18: VPL @ TMA estresse (R$) | B18: {=NPV(Premissas!$B$5,B10:B14)+B9} -> -453460.39 | C18: {=NPV(Premissas!$B$5,C10:C14)+C9} -> 1292917.3 | D18: {=NPV(Premissas!$B$5,D10:D14)+D9} -> 2950933.5
A19: TIR (a.a.) | B19: =IRR(B9:B14) -> -0.013737862 | C19: =IRR(C9:C14) -> 0.91471576 | D19: =IRR(D9:D14) -> 1.5892368
A20: Viável? (VPL rec. > 0) | B20: =IF(B16>0,"Sim","Não") -> Não | C20: =IF(C16>0,"Sim","Não") -> Sim | D20: =IF(D16>0,"Sim","Não") -> Sim
A22: Leitura: se a adoção ficar ~40% abaixo (pessimista), o VPL fica negativo — o risco nº 1 é a velocidade de aquisição de hectares.
